cyberprime/__init__.py
cyberprime/cyberprime.py
cyberprime/utils/__init__.py
cyberprime/utils/math_funs.py
cyberprime-0.0.3.dist-info/LICENSE
cyberprime-0.0.3.dist-info/METADATA
cyberprime-0.0.3.dist-info/WHEEL
cyberprime-0.0.3.dist-info/top_level.txt
cyberprime-0.0.3.dist-info/RECORD
