Metadata-Version: 2.1
Name: cyberprime
Version: 0.0.3
Summary: test buiding packages
Home-page: UNKNOWN
Author: Blank
Author-email: <blank@dineonwine.com>
License: UNKNOWN
Keywords: python,useless
Platform: UNKNOWN
Classifier: Development Status :: 1 - Planning
Classifier: Intended Audience :: Developers
Classifier: Programming Language :: Python :: 3
Classifier: Operating System :: Unix
Classifier: Operating System :: MacOS :: MacOS X
Classifier: Operating System :: Microsoft :: Windows
License-File: LICENSE
Requires-Dist: matplotlib
Requires-Dist: numpy
